[
{
  "model": "models.modelconfig",
  "pk": 5,
  "fields": {
    "created_at": "2017-07-21T19:52:53.385Z",
    "title": null,
    "production_firm_structure": {
      "salary": true,
      "labor_capacity": false,
      "salary_budget": false,
      "plan": false,
      "raw_need": null,
      "capital_need": null,
      "price": true,
      "capital_budget": null,
      "raw_budget": null
    },
    "raw_firm_structure": {
      "salary": true,
      "labor_capacity": false,
      "salary_budget": false,
      "plan": false,
      "price": true
    },
    "capital_firm_structure": {
      "salary": true,
      "labor_capacity": false,
      "salary_budget": false,
      "plan": false,
      "price": true,
      "raw_need": null,
      "raw_budget": null
    },
    "household_structure": {
      "consumption_budget": false,
      "consumption_need": false
    },
    "government_structure": {
      "import_tax": false,
      "minimal_tax": false,
      "coefficient_help": false,
      "income_tax": false,
      "profit_tax": false
    },
    "outside_world": false
  }
}
]